hex_renderer_py-0.1.5.dist-info/METADATA
hex_renderer_py-0.1.5.dist-info/WHEEL
hex_renderer_py-0.1.5.dist-info/licenses/LICENSE
hex_renderer_py/__init__.py
hex_renderer_py/__init__.pyi
hex_renderer_py/hex_renderer_py.cpython-310-x86_64-linux-gnu.so
hex_renderer_py/py.typed
hex_renderer_py-0.1.5.dist-info/RECORD
